setup.py
algdq/__init__.py
algdq.egg-info/PKG-INFO
algdq.egg-info/SOURCES.txt
algdq.egg-info/dependency_links.txt
algdq.egg-info/top_level.txt