Metadata-Version: 2.1
Name: algdq
Version: 0.0.6
Summary: 奥利给读取库
Home-page: https://alggfzslt.freeflarum.com/
Author: algfwq
Author-email: 3104374883@qq.com
License: MIT License
Platform: UNKNOWN
